CHANGELOG.md
CONTRIBUTING.md
COPYING
INSTALL.md
MANIFEST.in
README.md
pyproject.toml
setup.cfg
setup.py
.reuse/dep5
LICENSES/Apache-2.0.txt
LICENSES/CC0-1.0.txt
surfraw_tools/__init__.py
surfraw_tools/_package.py
surfraw_tools/mkelvis.py
surfraw_tools/opensearch2elvis.py
surfraw_tools.egg-info/PKG-INFO
surfraw_tools.egg-info/SOURCES.txt
surfraw_tools.egg-info/dependency_links.txt
surfraw_tools.egg-info/entry_points.txt
surfraw_tools.egg-info/not-zip-safe
surfraw_tools.egg-info/requires.txt
surfraw_tools.egg-info/top_level.txt
surfraw_tools/lib/__init__.py
surfraw_tools/lib/cliopts.py
surfraw_tools/lib/common.py
surfraw_tools/lib/elvis.py
surfraw_tools/lib/options.py
surfraw_tools/lib/validation.py
surfraw_tools/templates/elvis.in