Metadata-Version: 2.1
Name: surfraw-tools
Version: 0.2.0
Summary: Command-line programs to make writing surfraw elvi easier
Home-page: https://github.com/Hoboneer/surfraw-tools
Author: Gabriel Lisaca
Author-email: gabriel.lisaca@gmail.com
License: Apache-2.0
Project-URL: Documentation, https://hoboneer.github.io/surfraw-tools/
Keywords: surfraw,shell,elvis,script,generate,opensearch
Platform: POSIX
Platform: Linux
Classifier: Development Status :: 3 - Alpha
Classifier: Operating System :: POSIX
Classifier: Environment :: Console
Classifier: Programming Language :: Python :: 3 :: Only
Classifier: Programming Language :: Python :: 3.7
Classifier: Programming Language :: Unix Shell
Classifier: License :: OSI Approved :: Apache Software License
Classifier: License :: DFSG approved
Classifier: Topic :: System :: Shells
Classifier: Topic :: Software Development :: Code Generators
Classifier: Topic :: Utilities
Classifier: Topic :: Internet
Classifier: Topic :: Internet :: WWW/HTTP
Requires-Python: >=3.7
